odoo_ule_handler/__init__.py
odoo_ule_handler/odoo_handler.py
odoo_ule_handler-0.0.9.dist-info/LICENSE
odoo_ule_handler-0.0.9.dist-info/METADATA
odoo_ule_handler-0.0.9.dist-info/WHEEL
odoo_ule_handler-0.0.9.dist-info/top_level.txt
odoo_ule_handler-0.0.9.dist-info/RECORD
