Metadata-Version: 2.1
Name: odoo-ule-handler
Version: 0.0.9
Summary: Get ULE's Odoo data
Home-page: https://github.com/Usurbilgo-Lanbide-Eskola/odoo-ule-handler
Author: Aitor Iturrioz
Author-email: iraiturrioz@lhusurbil.eus
License: MIT
Download-URL: https://pypi.org/project/odoo-ule-handler/
Platform: UNKNOWN
Classifier: License :: OSI Approved :: MIT License
Classifier: Programming Language :: Python
Classifier: Programming Language :: Python :: 3
